core_db/__init__.py
core_db/py.typed
core_db/engines/__init__.py
core_db/engines/db2.py
core_db/engines/mongo.py
core_db/engines/mssql.py
core_db/engines/mysql.py
core_db/engines/oracle.py
core_db/engines/postgres.py
core_db/engines/snowflake_.py
core_db/etls/__init__.py
core_db/etls/database_based.py
core_db/interfaces/__init__.py
core_db/interfaces/base.py
core_db/interfaces/sql_based.py
core_db-3.0.1.dist-info/licenses/LICENSE
core_db-3.0.1.dist-info/METADATA
core_db-3.0.1.dist-info/WHEEL
core_db-3.0.1.dist-info/top_level.txt
core_db-3.0.1.dist-info/RECORD
