Metadata-Version: 2.4
Name: core-db
Version: 3.0.1
Summary: This project/library contains common elements and clients related to database engines...
Author-email: Alejandro Cora González <alek.cora.glez@gmail.com>
Maintainer: Alejandro Cora González
License-Expression: MIT
Project-URL: Homepage, https://gitlab.com/bytecode-solutions/core/core-db
Project-URL: Repository, https://gitlab.com/bytecode-solutions/core/core-db
Project-URL: Documentation, https://core-db.readthedocs.io/en/latest/
Project-URL: Issues, https://gitlab.com/bytecode-solutions/core/core-db/-/issues
Project-URL: Changelog, https://gitlab.com/bytecode-solutions/core/core-db/-/blob/master/CHANGELOG.md
Classifier: Intended Audience :: Developers
Classifier: Development Status :: 5 - Production/Stable
Classifier: Topic :: Software Development :: Libraries :: Python Modules
Classifier: Topic :: Utilities
Classifier: Programming Language :: Python :: 3
Classifier: Programming Language :: Python :: 3 :: Only
Classifier: Programming Language :: Python :: 3.9
Classifier: Programming Language :: Python :: 3.10
Classifier: Programming Language :: Python :: 3.11
Classifier: Programming Language :: Python :: 3.12
Classifier: Programming Language :: Python :: 3.13
Requires-Python: >=3.9
License-File: LICENSE
Requires-Dist: core-etl>=3.0.0
Requires-Dist: core-mixins>=2.2.2
Provides-Extra: all
Requires-Dist: PyMySQL>=1.1.1; extra == "all"
Requires-Dist: psycopg>=3.2.3; extra == "all"
Requires-Dist: psycopg-binary>=3.2.3; extra == "all"
Requires-Dist: oracledb>=2.5.0; extra == "all"
Requires-Dist: pyodbc>=5.2.0; extra == "all"
Requires-Dist: pymongo>=4.6.0; extra == "all"
Requires-Dist: ibm-db>=3.2.3; extra == "all"
Requires-Dist: snowflake-connector-python>=3.13.1; extra == "all"
Provides-Extra: dev
Requires-Dist: core-dev-tools>=1.0.1; extra == "dev"
Requires-Dist: core-tests>=2.0.3; extra == "dev"
Requires-Dist: types-ibm-db>=3.2.3.20241212; extra == "dev"
Provides-Extra: mysql
Requires-Dist: PyMySQL>=1.1.1; extra == "mysql"
Provides-Extra: postgres
Requires-Dist: psycopg>=3.2.3; extra == "postgres"
Requires-Dist: psycopg-binary>=3.2.3; extra == "postgres"
Provides-Extra: oracle
Requires-Dist: oracledb>=2.5.0; extra == "oracle"
Provides-Extra: mssql
Requires-Dist: pyodbc>=5.2.0; extra == "mssql"
Provides-Extra: mongo
Requires-Dist: pymongo>=4.6.0; extra == "mongo"
Provides-Extra: snowflake
Requires-Dist: snowflake-connector-python>=3.13.1; extra == "snowflake"
Provides-Extra: db2
Requires-Dist: ibm-db>=3.2.3; extra == "db2"
Dynamic: license-file
